banktransfer_fi/__init__.py
banktransfer_fi/payment.py
banktransfer_fi/signals.py
banktransfer_fi/viitenumero.py
banktransfer_fi/templates/banktransfer_fi/checkout_payment_form.html
banktransfer_fi/templates/banktransfer_fi/control.html
banktransfer_fi/templates/banktransfer_fi/pending.html
banktransfer_fi/templates/banktransfer_fi/email/order_pending.txt
pretix_banktransfer_fi-1.0.1.dist-info/LICENSE.txt
pretix_banktransfer_fi-1.0.1.dist-info/METADATA
pretix_banktransfer_fi-1.0.1.dist-info/RECORD
pretix_banktransfer_fi-1.0.1.dist-info/WHEEL
pretix_banktransfer_fi-1.0.1.dist-info/entry_points.txt
pretix_banktransfer_fi-1.0.1.dist-info/top_level.txt
