Metadata-Version: 2.1
Name: pretix-banktransfer-fi
Version: 1.0.1
Summary: Pretix plugin that creates a reference number (viitenumero) compliant with Finnish banks.
Home-page: https://github.com/fmorato/pretix-banktransfer-fi
Author: Felipe Morato
Author-email: me@fmorato.com
License: Apache Software License
Platform: UNKNOWN
